LICENSE.txt
MANIFEST.in
README.md
setup.py
django_pytest/__init__.py
django_pytest/auth_funcargs.py
django_pytest/conftest.py
django_pytest/models.py
django_pytest/test_runner.py
django_pytest.egg-info/PKG-INFO
django_pytest.egg-info/SOURCES.txt
django_pytest.egg-info/dependency_links.txt
django_pytest.egg-info/not-zip-safe
django_pytest.egg-info/top_level.txt
django_pytest/management/__init__.py
django_pytest/management/commands/__init__.py
django_pytest/management/commands/pytest.py
django_pytest/management/commands/test.py