Metadata-Version: 1.0
Name: django-pytest
Version: 0.2.0
Summary: django test runner to use py.test tests
Home-page: http://github.com/buchuki/django-pytest
Author: Dusty Phillips
Author-email: dusty@archlinux.ca
License: LICENSE.txt
Platform: UNKNOWN
